{
	"Version": 3,
	"Meta": {
		"Duration": 10.567,
		"Fps": 30.0,
		"Loop": true,
		"AreBeziersRestricted": true,
		"CurveCount": 11,
		"TotalSegmentCount": 148,
		"TotalPointCount": 425,
		"UserDataCount": 0,
		"TotalUserDataSize": 0
	},
	"Curves": [
		{
			"Target": "Model",
			"Id": "LipSync",
			"Segments": [
				0,
				0.004,
				1,
				0.022,
				0.004,
				0.044,
				0.008,
				0.067,
				0.008,
				1,
				0.111,
				0.008,
				0.156,
				0.008,
				0.2,
				0.008,
				1,
				0.222,
				0.008,
				0.244,
				0.267,
				0.267,
				0.267,
				1,
				0.289,
				0.267,
				0.311,
				0.012,
				0.333,
				0.012,
				1,
				0.356,
				0.012,
				0.378,
				0.318,
				0.4,
				0.318,
				1,
				0.444,
				0.318,
				0.489,
				0.157,
				0.533,
				0.157,
				1,
				0.556,
				0.157,
				0.578,
				0.416,
				0.6,
				0.416,
				1,
				0.644,
				0.416,
				0.689,
				0.008,
				0.733,
				0.008,
				1,
				0.778,
				0.008,
				0.822,
				0.329,
				0.867,
				0.329,
				1,
				0.889,
				0.329,
				0.911,
				0.275,
				0.933,
				0.275,
				1,
				0.978,
				0.275,
				1.022,
				0.396,
				1.067,
				0.396,
				1,
				1.133,
				0.396,
				1.2,
				0.008,
				1.267,
				0.008,
				1,
				1.311,
				0.008,
				1.356,
				0.008,
				1.4,
				0.008,
				1,
				1.422,
				0.008,
				1.444,
				0.012,
				1.467,
				0.012,
				1,
				1.489,
				0.012,
				1.511,
				0.008,
				1.533,
				0.008,
				1,
				1.556,
				0.008,
				1.578,
				0.008,
				1.6,
				0.008,
				1,
				1.622,
				0.008,
				1.644,
				0.525,
				1.667,
				0.525,
				1,
				1.756,
				0.525,
				1.844,
				0.008,
				1.933,
				0.008,
				1,
				1.956,
				0.008,
				1.978,
				0.008,
				2,
				0.008,
				1,
				2.044,
				0.008,
				2.089,
				0.149,
				2.133,
				0.149,
				1,
				2.156,
				0.149,
				2.178,
				0.008,
				2.2,
				0.008,
				1,
				2.311,
				0.008,
				2.422,
				0.267,
				2.533,
				0.267,
				1,
				2.556,
				0.267,
				2.578,
				0.031,
				2.6,
				0.031,
				1,
				2.622,
				0.031,
				2.644,
				0.078,
				2.667,
				0.078,
				1,
				2.711,
				0.078,
				2.756,
				0.008,
				2.8,
				0.008,
				1,
				2.822,
				0.008,
				2.844,
				0.008,
				2.867,
				0.008,
				1,
				2.911,
				0.008,
				2.956,
				0.075,
				3,
				0.075,
				1,
				3.044,
				0.075,
				3.089,
				0.008,
				3.133,
				0.008,
				1,
				3.222,
				0.008,
				3.311,
				0.008,
				3.4,
				0.008,
				1,
				3.422,
				0.008,
				3.444,
				0.004,
				3.467,
				0.004,
				1,
				3.489,
				0.004,
				3.511,
				0.004,
				3.533,
				0.004,
				1,
				3.556,
				0.004,
				3.578,
				0.008,
				3.6,
				0.008,
				1,
				3.622,
				0.008,
				3.644,
				0.008,
				3.667,
				0.008,
				1,
				3.689,
				0.008,
				3.711,
				0.012,
				3.733,
				0.012,
				1,
				3.756,
				0.012,
				3.778,
				0.008,
				3.8,
				0.008,
				1,
				3.822,
				0.008,
				3.844,
				0.008,
				3.867,
				0.008,
				1,
				3.889,
				0.008,
				3.911,
				0.012,
				3.933,
				0.012,
				1,
				3.956,
				0.012,
				3.978,
				0.008,
				4,
				0.008,
				1,
				4.044,
				0.008,
				4.089,
				0.008,
				4.133,
				0.008,
				1,
				4.156,
				0.008,
				4.178,
				0.016,
				4.2,
				0.016,
				1,
				4.222,
				0.016,
				4.244,
				0.008,
				4.267,
				0.008,
				1,
				4.289,
				0.008,
				4.311,
				0.008,
				4.333,
				0.008,
				1,
				4.356,
				0.008,
				4.378,
				0.004,
				4.4,
				0.004,
				1,
				4.422,
				0.004,
				4.444,
				0.008,
				4.467,
				0.008,
				1,
				4.489,
				0.008,
				4.511,
				0.008,
				4.533,
				0.008,
				1,
				4.578,
				0.008,
				4.622,
				0.325,
				4.667,
				0.325,
				1,
				4.8,
				0.325,
				4.933,
				0.008,
				5.067,
				0.008,
				1,
				5.089,
				0.008,
				5.111,
				0.012,
				5.133,
				0.012,
				1,
				5.156,
				0.012,
				5.178,
				0.008,
				5.2,
				0.008,
				1,
				5.222,
				0.008,
				5.244,
				0.012,
				5.267,
				0.012,
				1,
				5.289,
				0.012,
				5.311,
				0.012,
				5.333,
				0.012,
				1,
				5.356,
				0.012,
				5.378,
				0.016,
				5.4,
				0.016,
				1,
				5.422,
				0.016,
				5.444,
				0.012,
				5.467,
				0.012,
				1,
				5.489,
				0.012,
				5.511,
				0.012,
				5.533,
				0.012,
				1,
				5.556,
				0.012,
				5.578,
				0.008,
				5.6,
				0.008,
				1,
				5.667,
				0.008,
				5.733,
				0.341,
				5.8,
				0.341,
				1,
				5.867,
				0.341,
				5.933,
				0.055,
				6,
				0.055,
				1,
				6.022,
				0.055,
				6.044,
				0.106,
				6.067,
				0.106,
				1,
				6.089,
				0.106,
				6.111,
				0.012,
				6.133,
				0.012,
				1,
				6.178,
				0.012,
				6.222,
				0.012,
				6.267,
				0.012,
				1,
				6.289,
				0.012,
				6.311,
				0.016,
				6.333,
				0.016,
				1,
				6.356,
				0.016,
				6.378,
				0.012,
				6.4,
				0.012,
				1,
				6.422,
				0.012,
				6.444,
				0.016,
				6.467,
				0.016,
				1,
				6.489,
				0.016,
				6.511,
				0.012,
				6.533,
				0.012,
				1,
				6.556,
				0.012,
				6.578,
				0.012,
				6.6,
				0.012,
				1,
				6.622,
				0.012,
				6.644,
				0.016,
				6.667,
				0.016,
				1,
				6.689,
				0.016,
				6.711,
				0.012,
				6.733,
				0.012,
				1,
				6.756,
				0.012,
				6.778,
				0.016,
				6.8,
				0.016,
				1,
				6.822,
				0.016,
				6.844,
				0.016,
				6.867,
				0.016,
				1,
				6.889,
				0.016,
				6.911,
				0.012,
				6.933,
				0.012,
				1,
				6.956,
				0.012,
				6.978,
				0.012,
				7,
				0.012,
				1,
				7.022,
				0.012,
				7.044,
				0.016,
				7.067,
				0.016,
				1,
				7.089,
				0.016,
				7.111,
				0.012,
				7.133,
				0.012,
				1,
				7.2,
				0.012,
				7.267,
				0.306,
				7.333,
				0.306,
				1,
				7.4,
				0.306,
				7.467,
				0.008,
				7.533,
				0.008,
				1,
				7.556,
				0.008,
				7.578,
				0.039,
				7.6,
				0.039,
				1,
				7.644,
				0.039,
				7.689,
				0.008,
				7.733,
				0.008,
				1,
				7.756,
				0.008,
				7.778,
				0.012,
				7.8,
				0.012,
				1,
				7.822,
				0.012,
				7.844,
				0.012,
				7.867,
				0.012,
				1,
				7.889,
				0.012,
				7.911,
				0.008,
				7.933,
				0.008,
				1,
				7.956,
				0.008,
				7.978,
				0.016,
				8,
				0.016,
				1,
				8.022,
				0.016,
				8.044,
				0.012,
				8.067,
				0.012,
				1,
				8.089,
				0.012,
				8.111,
				0.012,
				8.133,
				0.012,
				1,
				8.178,
				0.012,
				8.222,
				0.024,
				8.267,
				0.024,
				1,
				8.289,
				0.024,
				8.311,
				0.012,
				8.333,
				0.012,
				1,
				8.4,
				0.012,
				8.467,
				0.012,
				8.533,
				0.012,
				1,
				8.556,
				0.012,
				8.578,
				0.008,
				8.6,
				0.008,
				1,
				8.622,
				0.008,
				8.644,
				0.008,
				8.667,
				0.008,
				1,
				8.689,
				0.008,
				8.711,
				0.012,
				8.733,
				0.012,
				1,
				8.756,
				0.012,
				8.778,
				0.008,
				8.8,
				0.008,
				1,
				8.822,
				0.008,
				8.844,
				0.012,
				8.867,
				0.012,
				1,
				8.889,
				0.012,
				8.911,
				0.008,
				8.933,
				0.008,
				1,
				8.956,
				0.008,
				8.978,
				0.012,
				9,
				0.012,
				1,
				9.022,
				0.012,
				9.044,
				0.012,
				9.067,
				0.012,
				1,
				9.089,
				0.012,
				9.111,
				0.004,
				9.133,
				0.004,
				1,
				9.156,
				0.004,
				9.178,
				0.008,
				9.2,
				0.008,
				1,
				9.222,
				0.008,
				9.244,
				0.004,
				9.267,
				0.004,
				1,
				9.311,
				0.004,
				9.356,
				0.545,
				9.4,
				0.545,
				1,
				9.422,
				0.545,
				9.444,
				0.259,
				9.467,
				0.259,
				1,
				9.489,
				0.259,
				9.511,
				0.314,
				9.533,
				0.314,
				1,
				9.556,
				0.314,
				9.578,
				0.012,
				9.6,
				0.012,
				1,
				9.644,
				0.012,
				9.689,
				0.227,
				9.733,
				0.227,
				1,
				9.756,
				0.227,
				9.778,
				0.192,
				9.8,
				0.192,
				1,
				9.844,
				0.192,
				9.889,
				0.325,
				9.933,
				0.325,
				1,
				9.956,
				0.325,
				9.978,
				0.012,
				10,
				0.012,
				1,
				10.089,
				0.012,
				10.178,
				0.012,
				10.267,
				0.012,
				1,
				10.289,
				0.012,
				10.311,
				0.008,
				10.333,
				0.008,
				1,
				10.378,
				0.008,
				10.422,
				0.016,
				10.467,
				0.016,
				1,
				10.489,
				0.016,
				10.511,
				0,
				10.533,
				0,
				0,
				10.567,
				0
			]
		},
		{
			"Target": "Parameter",
			"Id": "ParamAngleX",
			"Segments": [
				0,
				0,
				0,
				4.467,
				0,
				1,
				4.722,
				0,
				4.978,
				30,
				5.233,
				30,
				1,
				6.544,
				30,
				7.856,
				30,
				9.167,
				30,
				1,
				9.344,
				30,
				9.522,
				0,
				9.7,
				0,
				0,
				10.567,
				0
			]
		},
		{
			"Target": "Parameter",
			"Id": "ParamAngleY",
			"Segments": [
				0,
				0,
				0,
				4.467,
				0,
				1,
				4.722,
				0,
				4.978,
				-30,
				5.233,
				-30,
				1,
				6.544,
				-30,
				7.856,
				-30,
				9.167,
				-30,
				1,
				9.344,
				-30,
				9.522,
				0,
				9.7,
				0,
				0,
				10.567,
				0
			]
		},
		{
			"Target": "Parameter",
			"Id": "ParamEyeLOpen",
			"Segments": [
				0,
				0.5,
				1,
				1.489,
				0.5,
				2.978,
				0.5,
				4.467,
				0.5,
				1,
				4.722,
				0.5,
				4.978,
				0.3,
				5.233,
				0.3,
				1,
				6.544,
				0.3,
				7.856,
				0.3,
				9.167,
				0.3,
				1,
				9.344,
				0.3,
				9.522,
				0.5,
				9.7,
				0.5,
				0,
				10.567,
				0.5
			]
		},
		{
			"Target": "Parameter",
			"Id": "ParamEyeROpen",
			"Segments": [
				0,
				0.5,
				1,
				1.489,
				0.5,
				2.978,
				0.5,
				4.467,
				0.5,
				1,
				4.722,
				0.5,
				4.978,
				0.3,
				5.233,
				0.3,
				1,
				6.544,
				0.3,
				7.856,
				0.3,
				9.167,
				0.3,
				1,
				9.344,
				0.3,
				9.522,
				0.5,
				9.7,
				0.5,
				0,
				10.567,
				0.5
			]
		},
		{
			"Target": "Parameter",
			"Id": "ParamEyeBallX",
			"Segments": [
				0,
				0,
				0,
				4.467,
				0,
				1,
				4.722,
				0,
				4.978,
				-0.4,
				5.233,
				-0.4,
				1,
				6.544,
				-0.4,
				7.856,
				-0.4,
				9.167,
				-0.4,
				1,
				9.344,
				-0.4,
				9.522,
				0,
				9.7,
				0,
				0,
				10.567,
				0
			]
		},
		{
			"Target": "Parameter",
			"Id": "ParamEyeBallY",
			"Segments": [
				0,
				0,
				0,
				4.467,
				0,
				1,
				4.722,
				0,
				4.978,
				-0.1,
				5.233,
				-0.1,
				1,
				6.544,
				-0.1,
				7.856,
				-0.1,
				9.167,
				-0.1,
				1,
				9.344,
				-0.1,
				9.522,
				0,
				9.7,
				0,
				0,
				10.567,
				0
			]
		},
		{
			"Target": "Parameter",
			"Id": "ParamBrowLAngle",
			"Segments": [
				0,
				0,
				0,
				10.567,
				0
			]
		},
		{
			"Target": "Parameter",
			"Id": "ParamBrowRAngle",
			"Segments": [
				0,
				0,
				0,
				10.567,
				0
			]
		},
		{
			"Target": "Parameter",
			"Id": "ParamMouthForm",
			"Segments": [
				0,
				0,
				1,
				1.489,
				0,
				2.978,
				0,
				4.467,
				0,
				1,
				4.722,
				0,
				4.978,
				1,
				5.233,
				1,
				1,
				6.544,
				1,
				7.856,
				1,
				9.167,
				1,
				1,
				9.533,
				1,
				9.9,
				0,
				10.267,
				0,
				0,
				10.567,
				0
			]
		},
		{
			"Target": "Parameter",
			"Id": "ParamCheek",
			"Segments": [
				0,
				0,
				0,
				10.567,
				0
			]
		}
	]
}